treesearchsolverpy/__init__.py
treesearchsolverpy/best_first_search.py
treesearchsolverpy/commons.py
treesearchsolverpy/depth_first_search.py
treesearchsolverpy/greedy.py
treesearchsolverpy/iterative_beam_search.py
treesearchsolverpy-0.0.5.dist-info/LICENSE
treesearchsolverpy-0.0.5.dist-info/METADATA
treesearchsolverpy-0.0.5.dist-info/WHEEL
treesearchsolverpy-0.0.5.dist-info/top_level.txt
treesearchsolverpy-0.0.5.dist-info/RECORD
