Metadata-Version: 2.1
Name: treesearchsolverpy
Version: 0.0.5
Summary: A solver based on Heuristic Tree Search
Home-page: https://github.com/fontanf/treesearchsolverpy
Author: Florian Fontan
Author-email: dev@florian-fontan.fr
License: UNKNOWN
Project-URL: Bug Tracker, https://github.com/fontanf/treesearchsolverpy/issues
Platform: UNKNOWN
Classifier: Programming Language :: Python :: 3
Classifier: License :: OSI Approved :: MIT License
Classifier: Operating System :: OS Independent
Requires-Python: >=3.6
License-File: LICENSE
Requires-Dist: sortedcontainers
